[
  {
    "id": "1740044027424",
    "title": "buổi sáng tốt lành nhá a🥰",
    "date": "2025-02-20",
    "author": "Admin",
    "description": "undefined",
    "tags": [
      "Mới"
    ],
    "image": "/assets/uploads/sample.jpg",
    "featured": "true",
    "slug": "buoi-sang-tot-lanh-nha-a",
    "filename": "buoi-sang-tot-lanh-nha-a.md",
    "body": "# 16:35\n\n\n# Tính năng GFM 🏆\n\n## Hỗ trợ danh sách kiểm tra\n- [x] Viết bài blog\n- [ ] Sửa lỗi code\n- [ ] Deploy website\n\n## 2️⃣ Hỗ trợ bảng 📊  \n| Tên     | Tuổi | Nghề nghiệp  |\n|---------|-----|-------------|\n| Nam     | 25  | Developer   |\n| Hoa     | 22  | Designer    |\n\n## 3️⃣ Tự động nhận diện link 🔗  \nTruy cập: www.example.com\n\n## 4️⃣ Hỗ trợ code highlight 💻  \n```javascript\nconsole.log(\"Hello GFM!\");"
  },
  {
    "id": "1740045365357",
    "title": "git diff posts.json",
    "date": "2025-02-20",
    "author": "Admin",
    "description": "Lorem ipsum dolor sit atmet",
    "tags": [
      "Mới"
    ],
    "image": "/assets/uploads/sample.jpg",
    "slug": "git-diff-postsjson",
    "filename": "git-diff-postsjson.md",
    "featured": "false"
  },
  {
    "id": "1740045402089",
    "title": "git diff posts.json",
    "date": "2025-02-20",
    "author": "Admin",
    "description": "Lorem ipsum dolor sit atmet",
    "tags": [
      "Mới"
    ],
    "image": "/assets/uploads/sample.jpg",
    "slug": "git-diff-postsjson",
    "filename": "git-diff-postsjson.md",
    "featured": "false"
  },
  {
    "id": "1740045443643",
    "title": "git diff posts.json",
    "date": "2025-02-20",
    "author": "Admin",
    "description": "Lorem ipsum dolor sit atmet\"\"",
    "tags": [
      "Mới"
    ],
    "image": "/assets/uploads/sample.jpg",
    "featured": "false",
    "slug": "git-diff-postsjson",
    "filename": "git-diff-postsjson.md",
    "body": "# git diff posts.json\n ![Hình ảnh](https://raw.githubusercontent.com/duongvanphi19/minimalist-blog/main/assets/uploads/1000060853.jpg) \nNội dung bài viết tại đây..."
  },
  {
    "id": "1740041937444",
    "title": "time",
    "date": "2025-02-20",
    "author": "Admin",
    "description": "undefined\"",
    "tags": [
      "Mới"
    ],
    "image": "/assets/uploads/sample.jpg",
    "featured": "true",
    "slug": "time",
    "filename": "time.md"
  },
  {
    "id": "1740046693723",
    "title": "post 1",
    "date": "2025-02-20",
    "author": "Admin",
    "description": "Lorem ipsum dolor sit atmet\"",
    "tags": [
      "Mới"
    ],
    "image": "/assets/uploads/sample.jpg",
    "featured": "false",
    "slug": "post-1",
    "filename": "post-1.md"
  },
  {
    "id": "1740041380810",
    "title": "now",
    "date": "2025-02-20",
    "author": "Admin",
    "tags": [
      "Mới"
    ],
    "image": "/assets/uploads/sample.jpg",
    "slug": "now",
    "filename": "now.md"
  },
  {
    "id": "1740054251745",
    "title": "better logic",
    "date": "2025-02-20",
    "author": "Admin",
    "description": "Lorem ipsum dolor sit atmet",
    "tags": [
      "Mới"
    ],
    "image": "/assets/uploads/sample.jpg",
    "slug": "better-logic",
    "filename": "better-logic.md",
    "featured": "false"
  },
  {
    "id": "1740054644490",
    "title": "19:30",
    "date": "2025-02-20",
    "author": "Admin",
    "description": "Lorem ipsum dolor sit atmet",
    "tags": [
      "Mới"
    ],
    "image": "/assets/uploads/sample.jpg",
    "featured": "false",
    "slug": "1930",
    "filename": "1930.md",
    "body": "# 20h58\n\nNội dung bài viết tại đây..."
  },
  {
    "id": "1740056508122",
    "title": "20h01",
    "date": "2025-02-20",
    "author": "Admin",
    "description": "undefined",
    "tags": [
      "Mới"
    ],
    "image": "/assets/uploads/sample.jpg",
    "featured": "true",
    "slug": "20h01",
    "filename": "20h01.md",
    "body": "# 20h10\n\n```javascript \nmarked.setOptions({\n    gfm: true, // Bật chế độ GitHub Flavored Markdown\n    breaks: true, // Xuống dòng với dấu xuống dòng bình thường\n    tables: true, // Hỗ trợ bảng\n    smartLists: true, // Tự động nhận diện danh sách thông minh\n    smartypants: true, // Tự động thay thế dấu nháy & ký tự đặc biệt\n});"
  },
  {
    "id": "1740093002784",
    "title": "e5533d",
    "date": "2025-02-20",
    "author": "Admin",
    "description": "Lorem ipsum dolor sit atmet",
    "tags": [
      "Mới"
    ],
    "image": "/assets/uploads/sample.jpg",
    "featured": "true",
    "slug": "e5533d",
    "filename": "e5533d.md"
  }
]